ascendex/__init__.py
ascendex/exceptions.py
ascendex/reconnecting_websocket.py
ascendex/rest_client.py
ascendex/util.py
ascendex/web_socket_client.py
python_ascendex-0.2.0.dist-info/LICENSE
python_ascendex-0.2.0.dist-info/WHEEL
python_ascendex-0.2.0.dist-info/METADATA
python_ascendex-0.2.0.dist-info/RECORD
