Metadata-Version: 2.1
Name: python-ascendex
Version: 0.2.0
Summary: Python API for AscendEx
License: MIT
Author: Jan Skoda
Author-email: skoda@jskoda.cz
Requires-Python: >=3.8,<4.0
Classifier: License :: OSI Approved :: MIT License
Classifier: Programming Language :: Python :: 3
Classifier: Programming Language :: Python :: 3.8
Classifier: Programming Language :: Python :: 3.9
Classifier: Programming Language :: Python :: 3.10
Classifier: Programming Language :: Python :: 3.11
Requires-Dist: aiosonic (>=0.16.1,<0.17.0)
Requires-Dist: chardet (>=4.0.0,<5.0.0)
Requires-Dist: ujson (>=5.1.0,<6.0.0)
Requires-Dist: websockets (>=11.0.2,<12)
